DjangoZhongwenWendang18Update20161127/README.md
DjangoZhongwenWendang18Update20161127/__init__.py
DjangoZhongwenWendang18Update20161127/__main__.py
DjangoZhongwenWendang18Update20161127/file.epub
DjangoZhongwenWendang18Update20161127/index.html
DjangoZhongwenWendang18Update20161127/css/__init__.py
DjangoZhongwenWendang18Update20161127/css/annotations.css
DjangoZhongwenWendang18Update20161127/css/main.css
DjangoZhongwenWendang18Update20161127/css/normalize.css
DjangoZhongwenWendang18Update20161127/css/popup.css
DjangoZhongwenWendang18Update20161127/font/__init__.py
DjangoZhongwenWendang18Update20161127/font/fontello.eot
DjangoZhongwenWendang18Update20161127/font/fontello.svg
DjangoZhongwenWendang18Update20161127/font/fontello.ttf
DjangoZhongwenWendang18Update20161127/font/fontello.woff
DjangoZhongwenWendang18Update20161127/img/__init__.py
DjangoZhongwenWendang18Update20161127/img/annotator-glyph-sprite.png
DjangoZhongwenWendang18Update20161127/img/annotator-icon-sprite.png
DjangoZhongwenWendang18Update20161127/img/apple-touch-icon.png
DjangoZhongwenWendang18Update20161127/img/cancelfullscreen.png
DjangoZhongwenWendang18Update20161127/img/close.png
DjangoZhongwenWendang18Update20161127/img/fullscreen.png
DjangoZhongwenWendang18Update20161127/img/loader.gif
DjangoZhongwenWendang18Update20161127/img/menu-icon.png
DjangoZhongwenWendang18Update20161127/img/save.png
DjangoZhongwenWendang18Update20161127/img/saved.png
DjangoZhongwenWendang18Update20161127/img/settings-s.png
DjangoZhongwenWendang18Update20161127/img/settings.png
DjangoZhongwenWendang18Update20161127/img/star.png
DjangoZhongwenWendang18Update20161127/js/__init__.py
DjangoZhongwenWendang18Update20161127/js/epub.js
DjangoZhongwenWendang18Update20161127/js/epub.min.js
DjangoZhongwenWendang18Update20161127/js/epub.min.map
DjangoZhongwenWendang18Update20161127/js/hooks.min.js
DjangoZhongwenWendang18Update20161127/js/hooks.min.map
DjangoZhongwenWendang18Update20161127/js/reader.js
django_zhongwen_wendang_1_8_update_20161127-2024.3.1.0.dist-info/METADATA
django_zhongwen_wendang_1_8_update_20161127-2024.3.1.0.dist-info/WHEEL
django_zhongwen_wendang_1_8_update_20161127-2024.3.1.0.dist-info/entry_points.txt
django_zhongwen_wendang_1_8_update_20161127-2024.3.1.0.dist-info/top_level.txt
django_zhongwen_wendang_1_8_update_20161127-2024.3.1.0.dist-info/RECORD
